carinsurance_calculator/__init__.py
carinsurance_calculator/carinsurance_calculator.py
insurance_calculator-0.1.0.dist-info/LICENSE
insurance_calculator-0.1.0.dist-info/METADATA
insurance_calculator-0.1.0.dist-info/WHEEL
insurance_calculator-0.1.0.dist-info/top_level.txt
insurance_calculator-0.1.0.dist-info/RECORD
